{
  "modelo": "iso-x notifier",
  "timestamp": "2026-06-02T15:13:34.241Z",
  "sugerencias": {
    "directo": {
      "query": "iso-x notifier",
      "cursorPos": null,
      "resultados": [
        "iso-x notifier",
        "iso-x notifier manual español",
        "iso-x notifier datasheet",
        "iso x notifier pdf",
        "iso x notifier manual",
        "modulo iso x notifier",
        "modulo aislador iso x notifier",
        "notifier iso x installation manual",
        "notifier iso x wiring diagram",
        "notifier iso x fault isolator module"
      ]
    },
    "directo_click": {
      "query": "iso-x notifier",
      "cursorPos": 0,
      "resultados": [
        "iso-x notifier",
        "iso-x notifier manual español",
        "iso-x notifier datasheet",
        "iso x notifier pdf",
        "iso x notifier manual",
        "modulo iso x notifier",
        "notifier iso x installation manual",
        "modulo aislador para lazo inteligente marca notifier modelo iso x",
        "notifier modelo iso x",
        "notifier iso x data sheet"
      ]
    },
    "wildcard_inicio": {
      "query": "*iso-x notifier",
      "cursorPos": null,
      "resultados": [
        "iso x notifier",
        "iso x notifier manual español",
        "iso x notifier pdf",
        "iso x notifier manual",
        "iso x notifier datasheet",
        "modulo iso x notifier",
        "modulo aislador iso x notifier",
        "notifier iso x installation manual",
        "notifier iso x wiring diagram",
        "notifier iso x fault isolator module"
      ]
    },
    "wildcard_extremos": {
      "query": "*iso-x notifier*",
      "cursorPos": 1,
      "resultados": [
        "iso x notifier",
        "iso x notifier manual español",
        "iso x notifier datasheet",
        "iso x notifier pdf",
        "iso x notifier manual",
        "modulo iso x notifier",
        "notifier iso x installation manual",
        "modulo aislador para lazo inteligente marca notifier modelo iso x",
        "notifier modelo iso x",
        "notifier iso x data sheet"
      ]
    }
  },
  "producto": "https://www.desitec.com.mx/modulo-iso-x/",
  "consulta": "iso-x notifier",
  "resumenProducto": "iso-x notifier",
  "totalSugerenciasUnicas": 16,
  "resultadosUnicos": [
    "iso-x notifier",
    "iso-x notifier manual español",
    "iso-x notifier datasheet",
    "iso x notifier pdf",
    "iso x notifier manual",
    "modulo iso x notifier",
    "modulo aislador iso x notifier",
    "notifier iso x installation manual",
    "notifier iso x wiring diagram",
    "notifier iso x fault isolator module",
    "modulo aislador para lazo inteligente marca notifier modelo iso x",
    "notifier modelo iso x",
    "notifier iso x data sheet",
    "iso x notifier",
    "iso x notifier manual español",
    "iso x notifier datasheet"
  ]
}